Workbook

Sheet Fazit
A1: Lohnt sich ein dynamischer Stromtarif für dich?
A2: Auswertung deines Stromzählers (27.01.2025 – 29.05.2026, Stundenwerte) mit den echten Börsenpreisen der jeweiligen Stunde.
A4: Ergebnis über den gesamten Messzeitraum
A5: Stunden mit Zählerdaten | B5: =Monate!$B$22 -> 11389
A6: Netzbezug (kWh) | B6: =Monate!$E$22 -> 2520.023
A7: Einspeisung (kWh) – bleibt bei beiden Tarifen gleich vergütet | B7: =Monate!$F$22 -> 5163.8794
A8: Arbeitspreis-Kosten mit dynamischem Tarif | B8: =Monate!$H$22 -> 821.92418
A9: Arbeitspreis-Kosten mit deinem Festpreis | B9: =Monate!$I$22 -> 730.80667
A10: Dein Ø Preis dynamisch – gewichtet nach deinem Verbrauch (ct/kWh) | B10: =Monate!$K$22 -> 32.615741
A11: Ø dynamischer Preis über alle Stunden (ct/kWh) | B11: =Monate!$L$22 -> 30.30025
A12: Dein Festpreis (ct/kWh) | B12: =Einstellungen!$B$5 -> 29
A13: Anteil deines Netzbezugs in Stunden, in denen dynamisch billiger war | B13: =Monate!$M$22 -> 0.16396073
A15: Ein ganzes Jahr (Jahresfenster aus Einstellungen, Lücken hochgerechnet, inkl. Grundgebühren & Smart Meter)
A16: Zeitraum | B16: =Einstellungen!$B$11&" bis "&Einstellungen!$B$12 -> 2025-06 bis 2026-05
A17: Netzbezug im Jahr (kWh) | B17: =Monate!$O$23 -> 1949.0503
A18: Dein Ø Preis dynamisch in diesem Jahr (ct/kWh) | B18: =Monate!$P$23/Monate!$O$23*100 -> 32.083709
A19: Jahreskosten dynamisch | B19: =Monate!$P$23+12*Einstellungen!$B$7+Einstellungen!$B$8 -> 846.32763
A20: Jahreskosten Festpreis | B20: =Monate!$Q$23+12*Einstellungen!$B$6 -> 709.22459
A21: Ersparnis pro Jahr mit dynamischem Tarif | B21: =B20-B19 -> -137.10304
A22: ENTSCHEIDUNG | B22: =IF(B21>0,"Dynamischer Tarif lohnt sich","Bleib bei deinem Festpreis von "&TEXT(Einstellungen!$B$5,"0.0")&" ct") -> Bleib bei deinem Festpreis von 29.0 ct
A23: Zusätzlich einmalig für den Smart-Meter-Einbau (nicht oben enthalten) | B23: =Einstellungen!$B$9 -> 100
A25: Ab wann würde sich dynamisch lohnen?
A26: Dein Festpreis müsste höher sein als (ct/kWh) | B26: =(B19-12*Einstellungen!$B$6)/B17*100 -> 36.034351
A27: …oder Netzentgelt/Aufschläge müssten um so viel niedriger sein (ct/kWh netto) | B27: =MAX(0,(B19-B20)/B17*100/(1+Einstellungen!$B$10)) -> 5.9112193
A29: Warum?
A30: Deine PV-Anlage (und seit ca. September 2025 dein Speicher) deckt genau die Mittagsstunden ab, in denen Börsenstrom billig ist. Aus dem Netz holst du Strom vor allem abends (17–23 Uhr ≈ 40 % deines Netzbezugs) und nachts – dann ist Börsenstrom am teuersten.
A31: Nur ein kleiner Teil deines Netzbezugs fiel in Stunden, in denen der dynamische Preis unter 29 ct lag (Zeile oben). In keinem einzigen der 17 Monate wäre dynamisch günstiger gewesen (Blatt „Monate“).
A32: Verschieben hilft kaum: Selbst wenn du die Hälfte deines Abendverbrauchs in die 3 billigsten Stunden jedes Tages legst, bleibt der Festpreis günstiger. E-Auto gezielt billig laden + Speicher im Winter nachts aus dem Netz laden brächte zusammen nur ca. 40–50 € im Jahr.
A33: Seit Juni 2026 sind die Börsenpreise deutlich höher (Monatsmittel ca. 10–16 ct statt 6–9 ct im Sommer 2025). Im Moment wäre dynamisch also eher noch teurer.
A35: Wichtige Hinweise
A36: • Der wichtigste Wert ist dein Netzentgelt (Arbeitspreis pro kWh). Eingesetzt sind Bundesdurchschnitte (8,6 ct 2025 / 7,3 ct 2026 netto). Trag deinen Wert im Blatt „Einstellungen“ ein. Allein beim Arbeitspreis würde dynamisch erst unter ca. 5–6 ct netto gewinnen (mit 2026er Börsenpreisen sogar erst unter ca. 4–5 ct) – so niedrig ist kaum ein Netzbetreiber.
A37: • Ein dynamischer Tarif nach deinen echten Stunden geht nur mit einem intelligenten Messsystem (Smart-Meter-Gateway). Dein Tasmota-Lesekopf am Zähler zählt dafür nicht – ohne Gateway rechnen Anbieter mit einem Standardprofil oder Monatsmittel ab.
A38: • Zählerdaten 27.01.2025 – 29.05.2026; 294 Stunden fehlen (2,5 %, Blatt „Datenlücken“). Juni bis Oktober 2026 fehlen im Export ganz – exportier die Statistik nochmal, dann lässt sich das nachrechnen.
A39: • Stundenmittel: Innerhalb einer Stunde verrechnet der Zähler-Mittelwert Bezug und Einspeisung. Dein echter Netzbezug ist daher etwas höher (geschätzt 10–20 %). Das spricht eher noch etwas mehr für den Festpreis.
A40: • In den Daten erkannt: Batteriespeicher seit ca. Ende August 2025, mehrstündige Verbraucher mit ca. 2,7–3 kW abends (E-Auto?), keine Wärmepumpe. Ob Anfang oder Ende der Stunde als Zeitstempel gilt, ändert das Ergebnis nur um ein paar Euro.

Sheet Einstellungen
A1: Einstellungen & Annahmen
A2: Gelb/blau = änderbar. Alle anderen Blätter rechnen automatisch neu.
A4: Allgemein
A5: Dein Festpreis (brutto, ct/kWh) | B5: 29 | D5: Deine Angabe
A6: Grundpreis Festtarif gesamt (brutto, €/Monat) | B6: 12 | D6: Annahme – bitte aus deinem Vertrag/deiner Rechnung eintragen
A7: Grundpreis dynamischer Tarif gesamt (brutto, €/Monat) | B7: 15.5 | D7: Annahme: inkl. Anbietergebühr, Netz-Grundpreis und Messung. Vergleichsportal 16.10.2026: Ostrom/Octopus 15,22 €, Tibber 16,49 €, Rabot 16,65 € (regional verschieden, stromvermittlung.de)
A8: Mehrkosten Smart-Meter-Gateway (iMSys) ggü. heutigem Zähler (brutto, €/Jahr) | B8: 35 | D8: §30/§35 MsbG: optionaler Einbau bis 60 €/Jahr statt max. 25 €/Jahr für deinen modernen Zähler. Ist deine PV > 7 kWp, kommt das iMSys ohnehin (Pflicht) – dann hier 0 eintragen
A9: Einmalige Kosten Smart-Meter-Einbau auf Wunsch (brutto, €) | B9: 100 | D9: §35 MsbG: höchstens 100 € einmalig
A10: Mehrwertsteuer | B10: 0.19 | D10: 19 %
A11: Jahresfenster für die Jahresrechnung: erster Monat (JJJJ-MM) | B11: 2025-06 | D11: Letzte 12 Monate mit Zählerdaten (mit Speicher ab ca. Sept. 2025). Alternative: 2025-02 bis 2026-01
A12: Jahresfenster: letzter Monat (JJJJ-MM) | B12: 2026-05 | D12: Sollte 11 Monate nach dem ersten liegen (= 12 Monate)
A14: Aufschläge auf den Börsenpreis beim dynamischen Tarif (netto, ct/kWh)
B15: 2025 | C15: 2026 | D15: Quelle / Hinweis
A16: Netzentgelt – Arbeitspreis (nur der Teil pro kWh) | B16: 8.6 | C16: 7.3 | D16: WICHTIGSTER WERT – bitte vom Preisblatt deines Netzbetreibers ('Niederspannung ohne Leistungsmessung'). Hier Bundesdurchschnitt: BNetzA-Monitoringbericht 2025 (10,72 ct inkl. Grundpreis-Anteil → ca. 8,6 ct Arbeitspreis); 2026 ca. 1,7–2 ct niedriger durch Bundeszuschuss Übertragungsnetze (§24c EnWG, BDEW-Strompreisanalyse 08/2026)
A17: Stromsteuer | B17: 2.05 | C17: 2.05 | D17: StromStG – für Haushalte 2025 und 2026 unverändert
A18: Konzessionsabgabe | B18: 1.66 | C18: 1.66 | D18: Durchschnitt (BDEW). Je nach Gemeindegröße: ≤25.000 EW 1,32 · ≤100.000 EW 1,59 · ≤500.000 EW 1,99 · >500.000 EW 2,39
A19: KWKG-Umlage | B19: 0.277 | C19: 0.446 | D19: netztransparenz.de / BDEW 08/2026
A20: Aufschlag besondere Netznutzung (ex §19 StromNEV) | B20: 1.558 | C20: 1.559 | D20: netztransparenz.de / BDEW 08/2026
A21: Offshore-Netzumlage | B21: 0.816 | C21: 0.941 | D21: netztransparenz.de / BDEW 08/2026
A22: Anbieter-Aufschlag auf den Börsenpreis | B22: 1.8 | C22: 1.8 | D22: Annahme ähnlich Tibber (ca. 1,8 ct netto); Markt laut Finanztip 0–3 ct brutto
A23: Summe Aufschläge netto | B23: =SUM(B16:B22) -> 16.761 | C23: =SUM(C16:C22) -> 15.756
A25: So wird gerechnet: Endpreis dynamisch (brutto) = (Börsenpreis der Stunde + Summe Aufschläge) × (1 + MwSt). Jahr 2025 oder 2026 nach deutscher Ortszeit.
A26: Der Festpreis von 29 ct enthält Netzentgelt, Steuern und Umlagen schon. Deshalb vergleichen wir nur die Arbeitspreise; die Grundpreise kommen im Fazit dazu.
A27: Die Einspeisevergütung deiner PV hängt nicht vom Stromtarif ab (§19 EEG) und ist darum nicht Teil des Vergleichs.
A28: Börsenpreise: Day-Ahead DE-LU (EPEX Spot) via Energy-Charts (Fraunhofer ISE), CC BY 4.0, Daten Bundesnetzagentur | SMARD.de. Seit 01.10.2025 Viertelstundenpreise – hier zu Stundenmitteln zusammengefasst; bei Stundenwerten deines Zählers ergibt das exakt dasselbe Ergebnis.
A29: Zählerdaten: Home-Assistant-Export (sensor.tasmota_ehz_power, Stundenmittel in W). Zeitstempel = Ende der Stunde (so exportiert Home Assistant ab Version 2025.11) – hier schon auf den Stundenbeginn umgerechnet.

Sheet Stundendaten
A1: Datum | B1: Uhrzeit (Beginn) | C1: Wochentag | D1: Zählerleistung Ø (W) + Bezug / − Einspeisung | E1: Netzbezug (kWh) | F1: Einspeisung (kWh) | G1: Strom aus dem Netz gezogen? | H1: Börsenpreis (€/MWh) | I1: Endpreis dynamisch (ct/kWh brutto) | J1: Kosten dynamisch (€) | K1: Kosten Festpreis (€) | L1: Dynamisch günstiger in dieser Stunde? | M1: Monat | N1: Jahr | O1: Stunde
A2: 45684 | B2: 20:00 | C2: Mo | D2: 535.2 | E2: =MAX(D2,0)/1000 -> 0.5352 | F2: =MAX(-D2,0)/1000 -> 0 | G2: =IF(E2>0,"ja","nein") -> ja | H2: 94.07 | I2: =(H2/10+IF(N2=2025,Einstellungen!$B$23,Einstellungen!$C$23))*(1+Einstellungen!$B$10) -> 31.13992 | J2: =E2*I2/100 -> 0.16666085 | K2: =E2*Einstellungen!$B$5/100 -> 0.155208 | L2: =IF(I2<Einstellungen!$B$5,"ja","nein") -> nein | M2: 2025-01 | N2: 2025 | O2: 20
A3: 45684 | B3: 21:00 | C3: Mo | D3: 575.6 | E3: =MAX(D3,0)/1000 -> 0.5756 | F3: =MAX(-D3,0)/1000 -> 0 | G3: =IF(E3>0,"ja","nein") -> ja | H3: 85.08 | I3: =(H3/10+IF(N3=2025,Einstellungen!$B$23,Einstellungen!$C$23))*(1+Einstellungen!$B$10) -> 30.07011 | J3: =E3*I3/100 -> 0.17308355 | K3: =E3*Einstellungen!$B$5/100 -> 0.166924 | L3: =IF(I3<Einstellungen!$B$5,"ja","nein") -> nein | M3: 2025-01 | N3: 2025 | O3: 21
A4: 45684 | B4: 22:00 | C4: Mo | D4: 553.8 | E4: =MAX(D4,0)/1000 -> 0.5538 | F4: =MAX(-D4,0)/1000 -> 0 | G4: =IF(E4>0,"ja","nein") -> ja | H4: 82.26 | I4: =(H4/10+IF(N4=2025,Einstellungen!$B$23,Einstellungen!$C$23))*(1+Einstellungen!$B$10) -> 29.73453 | J4: =E4*I4/100 -> 0.16466983 | K4: =E4*Einstellungen!$B$5/100 -> 0.160602 | L4: =IF(I4<Einstellungen!$B$5,"ja","nein") -> nein | M4: 2025-01 | N4: 2025 | O4: 22
A5: 45685 | B5: 17:00 | C5: Di | D5: 412.8 | E5: =MAX(D5,0)/1000 -> 0.4128 | F5: =MAX(-D5,0)/1000 -> 0 | G5: =IF(E5>0,"ja","nein") -> ja | H5: 149.6 | I5: =(H5/10+IF(N5=2025,Einstellungen!$B$23,Einstellungen!$C$23))*(1+Einstellungen!$B$10) -> 37.74799 | J5: =E5*I5/100 -> 0.1558237 | K5: =E5*Einstellungen!$B$5/100 -> 0.119712 | L5: =IF(I5<Einstellungen!$B$5,"ja","nein") -> nein | M5: 2025-01 | N5: 2025 | O5: 17
A6: 45685 | B6: 18:00 | C6: Di | D6: 412.8 | E6: =MAX(D6,0)/1000 -> 0.4128 | F6: =MAX(-D6,0)/1000 -> 0 | G6: =IF(E6>0,"ja","nein") -> ja | H6: 134.94 | I6: =(H6/10+IF(N6=2025,Einstellungen!$B$23,Einstellungen!$C$23))*(1+Einstellungen!$B$10) -> 36.00345 | J6: =E6*I6/100 -> 0.14862224 | K6: =E6*Einstellungen!$B$5/100 -> 0.119712 | L6: =IF(I6<Einstellungen!$B$5,"ja","nein") -> nein | M6: 2025-01 | N6: 2025 | O6: 18
A7: 45685 | B7: 19:00 | C7: Di | D7: 478.4 | E7: =MAX(D7,0)/1000 -> 0.4784 | F7: =MAX(-D7,0)/1000 -> 0 | G7: =IF(E7>0,"ja","nein") -> ja | H7: 128.9 | I7: =(H7/10+IF(N7=2025,Einstellungen!$B$23,Einstellungen!$C$23))*(1+Einstellungen!$B$10) -> 35.28469 | J7: =E7*I7/100 -> 0.16880196 | K7: =E7*Einstellungen!$B$5/100 -> 0.138736 | L7: =IF(I7<Einstellungen!$B$5,"ja","nein") -> nein | M7: 2025-01 | N7: 2025 | O7: 19
A8: 45685 | B8: 20:00 | C8: Di | D8: 454.2 | E8: =MAX(D8,0)/1000 -> 0.4542 | F8: =MAX(-D8,0)/1000 -> 0 | G8: =IF(E8>0,"ja","nein") -> ja | H8: 94.76 | I8: =(H8/10+IF(N8=2025,Einstellungen!$B$23,Einstellungen!$C$23))*(1+Einstellungen!$B$10) -> 31.22203 | J8: =E8*I8/100 -> 0.14181046 | K8: =E8*Einstellungen!$B$5/100 -> 0.131718 | L8: =IF(I8<Einstellungen!$B$5,"ja","nein") -> nein | M8: 2025-01 | N8: 2025 | O8: 20
A9: 45685 | B9: 22:00 | C9: Di | D9: 241.4 | E9: =MAX(D9,0)/1000 -> 0.2414 | F9: =MAX(-D9,0)/1000 -> 0 | G9: =IF(E9>0,"ja","nein") -> ja | H9: 79.8 | I9: =(H9/10+IF(N9=2025,Einstellungen!$B$23,Einstellungen!$C$23))*(1+Einstellungen!$B$10) -> 29.44179 | J9: =E9*I9/100 -> 0.071072481 | K9: =E9*Einstellungen!$B$5/100 -> 0.070006 | L9: =IF(I9<Einstellungen!$B$5,"ja","nein") -> nein | M9: 2025-01 | N9: 2025 | O9: 22
A10: 45685 | B10: 23:00 | C10: Di | D10: 262.1 | E10: =MAX(D10,0)/1000 -> 0.2621 | F10: =MAX(-D10,0)/1000 -> 0 | G10: =IF(E10>0,"ja","nein") -> ja | H10: 64.43 | I10: =(H10/10+IF(N10=2025,Einstellungen!$B$23,Einstellungen!$C$23))*(1+Einstellungen!$B$10) -> 27.61276 | J10: =E10*I10/100 -> 0.072373044 | K10: =E10*Einstellungen!$B$5/100 -> 0.076009 | L10: =IF(I10<Einstellungen!$B$5,"ja","nein") -> ja | M10: 2025-01 | N10: 2025 | O10: 23
A11: 45686 | B11: 00:00 | C11: Mi | D11: 200.6 | E11: =MAX(D11,0)/1000 -> 0.2006 | F11: =MAX(-D11,0)/1000 -> 0 | G11: =IF(E11>0,"ja","nein") -> ja | H11: 87.72 | I11: =(H11/10+IF(N11=2025,Einstellungen!$B$23,Einstellungen!$C$23))*(1+Einstellungen!$B$10) -> 30.38427 | J11: =E11*I11/100 -> 0.060950846 | K11: =E11*Einstellungen!$B$5/100 -> 0.058174 | L11: =IF(I11<Einstellungen!$B$5,"ja","nein") -> nein | M11: 2025-01 | N11: 2025 | O11: 0
A12: 45686 | B12: 15:00 | C12: Mi | D12: -825.3 | E12: =MAX(D12,0)/1000 -> 0 | F12: =MAX(-D12,0)/1000 -> 0.8253 | G12: =IF(E12>0,"ja","nein") -> nein | H12: 102.75 | I12: =(H12/10+IF(N12=2025,Einstellungen!$B$23,Einstellungen!$C$23))*(1+Einstellungen!$B$10) -> 32.17284 | J12: =E12*I12/100 -> 0 | K12: =E12*Einstellungen!$B$5/100 -> 0 | L12: =IF(I12<Einstellungen!$B$5,"ja","nein") -> nein | M12: 2025-01 | N12: 2025 | O12: 15
A13: 45686 | B13: 16:00 | C13: Mi | D13: -131.1 | E13: =MAX(D13,0)/1000 -> 0 | F13: =MAX(-D13,0)/1000 -> 0.1311 | G13: =IF(E13>0,"ja","nein") -> nein | H13: 132.66 | I13: =(H13/10+IF(N13=2025,Einstellungen!$B$23,Einstellungen!$C$23))*(1+Einstellungen!$B$10) -> 35.73213 | J13: =E13*I13/100 -> 0 | K13: =E13*Einstellungen!$B$5/100 -> 0 | L13: =IF(I13<Einstellungen!$B$5,"ja","nein") -> nein | M13: 2025-01 | N13: 2025 | O13: 16
... A11390: 46171 | B11390: 15:00 | C11390: Fr | D11390: -3324.5 | E11390: =MAX(D11390,0)/1000 -> 0 | F11390: =MAX(-D11390,0)/1000 -> 3.3245 | G11390: =IF(E11390>0,"ja","nein") -> nein | H11390: 9.41 | I11390: =(H11390/10+IF(N11390=2025,Einstellungen!$B$23,Einstellungen!$C$23))*(1+Einstellungen!$B$10) -> 19.86943 | J11390: =E11390*I11390/100 -> 0 | K11390: =E11390*Einstellungen!$B$5/100 -> 0 | L11390: =IF(I11390<Einstellungen!$B$5,"ja","nein") -> ja | M11390: 2026-05 | N11390: 2026 | O11390: 15

Sheet Monate
A1: Monat für Monat – dein echter Verbrauch
A2: Spalten B–M: nur Stunden mit Zählerdaten. Spalten O–Q: auf den vollen Monat hochgerechnet (fehlende Stunden wie der Rest des Monats). Grün = dynamisch wäre günstiger gewesen. Ohne Grundpreise (siehe Fazit).
A4: Monat | B4: Stunden mit Daten | C4: Stunden im Monat | D4: Fehlende Stunden | E4: Netzbezug (kWh) | F4: Einspeisung (kWh) | G4: Stunden mit Netzbezug | H4: Kosten dynamisch (€) | I4: Kosten Festpreis (€) | J4: Ersparnis dynamisch (€) | K4: Ø dyn. Preis, gewichtet nach deinem Bezug (ct/kWh) | L4: Ø dyn. Preis aller Stunden (ct/kWh) | M4: Anteil Bezug in Stunden < Festpreis | N4: Im Jahresfenster? | O4: Netzbezug hochgerechnet (kWh) | P4: Kosten dynamisch hochgerechnet (€) | Q4: Kosten Festpreis hochgerechnet (€)
A5: 2025-01 | B5: =COUNTIF(Stundendaten!$M$2:$M$11390,A5) -> 67 | C5: 744 | D5: =C5-B5 -> 677 | E5: =SUMIF(Stundendaten!$M$2:$M$11390,A5,Stundendaten!$E$2:$E$11390) -> 33.6347 | F5: =SUMIF(Stundendaten!$M$2:$M$11390,A5,Stundendaten!$F$2:$F$11390) -> 14.0124 | G5: =COUNTIFS(Stundendaten!$M$2:$M$11390,A5,Stundendaten!$G$2:$G$11390,"ja") -> 52 | H5: =SUMIF(Stundendaten!$M$2:$M$11390,A5,Stundendaten!$J$2:$J$11390) -> 12.361207 | I5: =SUMIF(Stundendaten!$M$2:$M$11390,A5,Stundendaten!$K$2:$K$11390) -> 9.754063 | J5: =I5-H5 -> -2.6071442 | K5: =IF(E5>0,H5/E5*100,0) -> 36.751353 | L5: =AVERAGEIF(Stundendaten!$M$2:$M$11390,A5,Stundendaten!$I$2:$I$11390) -> 35.374793 | M5: =IF(E5>0,SUMIFS(Stundendaten!$E$2:$E$11390,Stundendaten!$M$2:$M$11390,A5,Stundendaten!$L$2:$L$11390,"ja")/E5,0) -> 0.0077925476 | N5: =IF(AND(A5>=Einstellungen!$B$11,A5<=Einstellungen!$B$12),"ja","nein") -> nein | O5: =IF(B5>0,E5*C5/B5,0) -> 373.49577 | P5: =IF(B5>0,H5*C5/B5,0) -> 137.26475 | Q5: =IF(B5>0,I5*C5/B5,0) -> 108.31377
A6: 2025-02 | B6: =COUNTIF(Stundendaten!$M$2:$M$11390,A6) -> 672 | C6: 672 | D6: =C6-B6 -> 0 | E6: =SUMIF(Stundendaten!$M$2:$M$11390,A6,Stundendaten!$E$2:$E$11390) -> 225.9624 | F6: =SUMIF(Stundendaten!$M$2:$M$11390,A6,Stundendaten!$F$2:$F$11390) -> 135.367 | G6: =COUNTIFS(Stundendaten!$M$2:$M$11390,A6,Stundendaten!$G$2:$G$11390,"ja") -> 590 | H6: =SUMIF(Stundendaten!$M$2:$M$11390,A6,Stundendaten!$J$2:$J$11390) -> 81.655427 | I6: =SUMIF(Stundendaten!$M$2:$M$11390,A6,Stundendaten!$K$2:$K$11390) -> 65.529096 | J6: =I6-H6 -> -16.126331 | K6: =IF(E6>0,H6/E6*100,0) -> 36.136732 | L6: =AVERAGEIF(Stundendaten!$M$2:$M$11390,A6,Stundendaten!$I$2:$I$11390) -> 35.239752 | M6: =IF(E6>0,SUMIFS(Stundendaten!$E$2:$E$11390,Stundendaten!$M$2:$M$11390,A6,Stundendaten!$L$2:$L$11390,"ja")/E6,0) -> 0.050253494 | N6: =IF(AND(A6>=Einstellungen!$B$11,A6<=Einstellungen!$B$12),"ja","nein") -> nein | O6: =IF(B6>0,E6*C6/B6,0) -> 225.9624 | P6: =IF(B6>0,H6*C6/B6,0) -> 81.655427 | Q6: =IF(B6>0,I6*C6/B6,0) -> 65.529096
A7: 2025-03 | B7: =COUNTIF(Stundendaten!$M$2:$M$11390,A7) -> 743 | C7: 743 | D7: =C7-B7 -> 0 | E7: =SUMIF(Stundendaten!$M$2:$M$11390,A7,Stundendaten!$E$2:$E$11390) -> 181.4315 | F7: =SUMIF(Stundendaten!$M$2:$M$11390,A7,Stundendaten!$F$2:$F$11390) -> 470.6621 | G7: =COUNTIFS(Stundendaten!$M$2:$M$11390,A7,Stundendaten!$G$2:$G$11390,"ja") -> 531 | H7: =SUMIF(Stundendaten!$M$2:$M$11390,A7,Stundendaten!$J$2:$J$11390) -> 60.983595 | I7: =SUMIF(Stundendaten!$M$2:$M$11390,A7,Stundendaten!$K$2:$K$11390) -> 52.615135 | J7: =I7-H7 -> -8.3684598 | K7: =IF(E7>0,H7/E7*100,0) -> 33.612462 | L7: =AVERAGEIF(Stundendaten!$M$2:$M$11390,A7,Stundendaten!$I$2:$I$11390) -> 31.218162 | M7: =IF(E7>0,SUMIFS(Stundendaten!$E$2:$E$11390,Stundendaten!$M$2:$M$11390,A7,Stundendaten!$L$2:$L$11390,"ja")/E7,0) -> 0.12902721 | N7: =IF(AND(A7>=Einstellungen!$B$11,A7<=Einstellungen!$B$12),"ja","nein") -> nein | O7: =IF(B7>0,E7*C7/B7,0) -> 181.4315 | P7: =IF(B7>0,H7*C7/B7,0) -> 60.983595 | Q7: =IF(B7>0,I7*C7/B7,0) -> 52.615135
A8: 2025-04 | B8: =COUNTIF(Stundendaten!$M$2:$M$11390,A8) -> 703 | C8: 720 | D8: =C8-B8 -> 17 | E8: =SUMIF(Stundendaten!$M$2:$M$11390,A8,Stundendaten!$E$2:$E$11390) -> 103.7771 | F8: =SUMIF(Stundendaten!$M$2:$M$11390,A8,Stundendaten!$F$2:$F$11390) -> 650.2096 | G8: =COUNTIFS(Stundendaten!$M$2:$M$11390,A8,Stundendaten!$G$2:$G$11390,"ja") -> 422 | H8: =SUMIF(Stundendaten!$M$2:$M$11390,A8,Stundendaten!$J$2:$J$11390) -> 33.616706 | I8: =SUMIF(Stundendaten!$M$2:$M$11390,A8,Stundendaten!$K$2:$K$11390) -> 30.095359 | J8: =I8-H8 -> -3.5213469 | K8: =IF(E8>0,H8/E8*100,0) -> 32.393183 | L8: =AVERAGEIF(Stundendaten!$M$2:$M$11390,A8,Stundendaten!$I$2:$I$11390) -> 29.135511 | M8: =IF(E8>0,SUMIFS(Stundendaten!$E$2:$E$11390,Stundendaten!$M$2:$M$11390,A8,Stundendaten!$L$2:$L$11390,"ja")/E8,0) -> 0.12388668 | N8: =IF(AND(A8>=Einstellungen!$B$11,A8<=Einstellungen!$B$12),"ja","nein") -> nein | O8: =IF(B8>0,E8*C8/B8,0) -> 106.28665 | P8: =IF(B8>0,H8*C8/B8,0) -> 34.429628 | Q8: =IF(B8>0,I8*C8/B8,0) -> 30.823127
A9: 2025-05 | B9: =COUNTIF(Stundendaten!$M$2:$M$11390,A9) -> 744 | C9: 744 | D9: =C9-B9 -> 0 | E9: =SUMIF(Stundendaten!$M$2:$M$11390,A9,Stundendaten!$E$2:$E$11390) -> 93.5057 | F9: =SUMIF(Stundendaten!$M$2:$M$11390,A9,Stundendaten!$F$2:$F$11390) -> 751.6315 | G9: =COUNTIFS(Stundendaten!$M$2:$M$11390,A9,Stundendaten!$G$2:$G$11390,"ja") -> 398 | H9: =SUMIF(Stundendaten!$M$2:$M$11390,A9,Stundendaten!$J$2:$J$11390) -> 29.4259 | I9: =SUMIF(Stundendaten!$M$2:$M$11390,A9,Stundendaten!$K$2:$K$11390) -> 27.116653 | J9: =I9-H9 -> -2.309247 | K9: =IF(E9>0,H9/E9*100,0) -> 31.469632 | L9: =AVERAGEIF(Stundendaten!$M$2:$M$11390,A9,Stundendaten!$I$2:$I$11390) -> 27.958887 | M9: =IF(E9>0,SUMIFS(Stundendaten!$E$2:$E$11390,Stundendaten!$M$2:$M$11390,A9,Stundendaten!$L$2:$L$11390,"ja")/E9,0) -> 0.19329517 | N9: =IF(AND(A9>=Einstellungen!$B$11,A9<=Einstellungen!$B$12),"ja","nein") -> nein | O9: =IF(B9>0,E9*C9/B9,0) -> 93.5057 | P9: =IF(B9>0,H9*C9/B9,0) -> 29.4259 | Q9: =IF(B9>0,I9*C9/B9,0) -> 27.116653
A10: 2025-06 | B10: =COUNTIF(Stundendaten!$M$2:$M$11390,A10) -> 708 | C10: 720 | D10: =C10-B10 -> 12 | E10: =SUMIF(Stundendaten!$M$2:$M$11390,A10,Stundendaten!$E$2:$E$11390) -> 73.061 | F10: =SUMIF(Stundendaten!$M$2:$M$11390,A10,Stundendaten!$F$2:$F$11390) -> 771.8992 | G10: =COUNTIFS(Stundendaten!$M$2:$M$11390,A10,Stundendaten!$G$2:$G$11390,"ja") -> 360 | H10: =SUMIF(Stundendaten!$M$2:$M$11390,A10,Stundendaten!$J$2:$J$11390) -> 23.454472 | I10: =SUMIF(Stundendaten!$M$2:$M$11390,A10,Stundendaten!$K$2:$K$11390) -> 21.18769 | J10: =I10-H10 -> -2.2667823 | K10: =IF(E10>0,H10/E10*100,0) -> 32.102589 | L10: =AVERAGEIF(Stundendaten!$M$2:$M$11390,A10,Stundendaten!$I$2:$I$11390) -> 27.530097 | M10: =IF(E10>0,SUMIFS(Stundendaten!$E$2:$E$11390,Stundendaten!$M$2:$M$11390,A10,Stundendaten!$L$2:$L$11390,"ja")/E10,0) -> 0.19621002 | N10: =IF(AND(A10>=Einstellungen!$B$11,A10<=Einstellungen!$B$12),"ja","nein") -> ja | O10: =IF(B10>0,E10*C10/B10,0) -> 74.299322 | P10: =IF(B10>0,H10*C10/B10,0) -> 23.852006 | Q10: =IF(B10>0,I10*C10/B10,0) -> 21.546803
A11: 2025-07 | B11: =COUNTIF(Stundendaten!$M$2:$M$11390,A11) -> 744 | C11: 744 | D11: =C11-B11 -> 0 | E11: =SUMIF(Stundendaten!$M$2:$M$11390,A11,Stundendaten!$E$2:$E$11390) -> 79.8467 | F11: =SUMIF(Stundendaten!$M$2:$M$11390,A11,Stundendaten!$F$2:$F$11390) -> 575.6507 | G11: =COUNTIFS(Stundendaten!$M$2:$M$11390,A11,Stundendaten!$G$2:$G$11390,"ja") -> 397 | H11: =SUMIF(Stundendaten!$M$2:$M$11390,A11,Stundendaten!$J$2:$J$11390) -> 26.029993 | I11: =SUMIF(Stundendaten!$M$2:$M$11390,A11,Stundendaten!$K$2:$K$11390) -> 23.155543 | J11: =I11-H11 -> -2.8744496 | K11: =IF(E11>0,H11/E11*100,0) -> 32.59996 | L11: =AVERAGEIF(Stundendaten!$M$2:$M$11390,A11,Stundendaten!$I$2:$I$11390) -> 30.393222 | M11: =IF(E11>0,SUMIFS(Stundendaten!$E$2:$E$11390,Stundendaten!$M$2:$M$11390,A11,Stundendaten!$L$2:$L$11390,"ja")/E11,0) -> 0.020109785 | N11: =IF(AND(A11>=Einstellungen!$B$11,A11<=Einstellungen!$B$12),"ja","nein") -> ja | O11: =IF(B11>0,E11*C11/B11,0) -> 79.8467 | P11: =IF(B11>0,H11*C11/B11,0) -> 26.029993 | Q11: =IF(B11>0,I11*C11/B11,0) -> 23.155543
A12: 2025-08 | B12: =COUNTIF(Stundendaten!$M$2:$M$11390,A12) -> 741 | C12: 744 | D12: =C12-B12 -> 3 | E12: =SUMIF(Stundendaten!$M$2:$M$11390,A12,Stundendaten!$E$2:$E$11390) -> 65.1122 | F12: =SUMIF(Stundendaten!$M$2:$M$11390,A12,Stundendaten!$F$2:$F$11390) -> 582.6588 | G12: =COUNTIFS(Stundendaten!$M$2:$M$11390,A12,Stundendaten!$G$2:$G$11390,"ja") -> 318 | H12: =SUMIF(Stundendaten!$M$2:$M$11390,A12,Stundendaten!$J$2:$J$11390) -> 21.119368 | I12: =SUMIF(Stundendaten!$M$2:$M$11390,A12,Stundendaten!$K$2:$K$11390) -> 18.882538 | J12: =I12-H12 -> -2.2368297 | K12: =IF(E12>0,H12/E12*100,0) -> 32.435347 | L12: =AVERAGEIF(Stundendaten!$M$2:$M$11390,A12,Stundendaten!$I$2:$I$11390) -> 29.118642 | M12: =IF(E12>0,SUMIFS(Stundendaten!$E$2:$E$11390,Stundendaten!$M$2:$M$11390,A12,Stundendaten!$L$2:$L$11390,"ja")/E12,0) -> 0.11717927 | N12: =IF(AND(A12>=Einstellungen!$B$11,A12<=Einstellungen!$B$12),"ja","nein") -> ja | O12: =IF(B12>0,E12*C12/B12,0) -> 65.375812 | P12: =IF(B12>0,H12*C12/B12,0) -> 21.204871 | Q12: =IF(B12>0,I12*C12/B12,0) -> 18.958986
A13: 2025-09 | B13: =COUNTIF(Stundendaten!$M$2:$M$11390,A13) -> 613 | C13: 720 | D13: =C13-B13 -> 107 | E13: =SUMIF(Stundendaten!$M$2:$M$11390,A13,Stundendaten!$E$2:$E$11390) -> 62.7625 | F13: =SUMIF(Stundendaten!$M$2:$M$11390,A13,Stundendaten!$F$2:$F$11390) -> 157.046 | G13: =COUNTIFS(Stundendaten!$M$2:$M$11390,A13,Stundendaten!$G$2:$G$11390,"ja") -> 262 | H13: =SUMIF(Stundendaten!$M$2:$M$11390,A13,Stundendaten!$J$2:$J$11390) -> 18.6996 | I13: =SUMIF(Stundendaten!$M$2:$M$11390,A13,Stundendaten!$K$2:$K$11390) -> 18.201125 | J13: =I13-H13 -> -0.49847474 | K13: =IF(E13>0,H13/E13*100,0) -> 29.794224 | L13: =AVERAGEIF(Stundendaten!$M$2:$M$11390,A13,Stundendaten!$I$2:$I$11390) -> 29.829293 | M13: =IF(E13>0,SUMIFS(Stundendaten!$E$2:$E$11390,Stundendaten!$M$2:$M$11390,A13,Stundendaten!$L$2:$L$11390,"ja")/E13,0) -> 0.40166819 | N13: =IF(AND(A13>=Einstellungen!$B$11,A13<=Einstellungen!$B$12),"ja","nein") -> ja | O13: =IF(B13>0,E13*C13/B13,0) -> 73.717781 | P13: =IF(B13>0,H13*C13/B13,0) -> 21.963641 | Q13: =IF(B13>0,I13*C13/B13,0) -> 21.378157
A14: 2025-10 | B14: =COUNTIF(Stundendaten!$M$2:$M$11390,A14) -> 745 | C14: 745 | D14: =C14-B14 -> 0 | E14: =SUMIF(Stundendaten!$M$2:$M$11390,A14,Stundendaten!$E$2:$E$11390) -> 144.7721 | F14: =SUMIF(Stundendaten!$M$2:$M$11390,A14,Stundendaten!$F$2:$F$11390) -> 59.4105 | G14: =COUNTIFS(Stundendaten!$M$2:$M$11390,A14,Stundendaten!$G$2:$G$11390,"ja") -> 390 | H14: =SUMIF(Stundendaten!$M$2:$M$11390,A14,Stundendaten!$J$2:$J$11390) -> 44.357404 | I14: =SUMIF(Stundendaten!$M$2:$M$11390,A14,Stundendaten!$K$2:$K$11390) -> 41.983909 | J14: =I14-H14 -> -2.3734955 | K14: =IF(E14>0,H14/E14*100,0) -> 30.63947 | L14: =AVERAGEIF(Stundendaten!$M$2:$M$11390,A14,Stundendaten!$I$2:$I$11390) -> 29.989432 | M14: =IF(E14>0,SUMIFS(Stundendaten!$E$2:$E$11390,Stundendaten!$M$2:$M$11390,A14,Stundendaten!$L$2:$L$11390,"ja")/E14,0) -> 0.38340398 | N14: =IF(AND(A14>=Einstellungen!$B$11,A14<=Einstellungen!$B$12),"ja","nein") -> ja | O14: =IF(B14>0,E14*C14/B14,0) -> 144.7721 | P14: =IF(B14>0,H14*C14/B14,0) -> 44.357404 | Q14: =IF(B14>0,I14*C14/B14,0) -> 41.983909
A15: 2025-11 | B15: =COUNTIF(Stundendaten!$M$2:$M$11390,A15) -> 711 | C15: 720 | D15: =C15-B15 -> 9 | E15: =SUMIF(Stundendaten!$M$2:$M$11390,A15,Stundendaten!$E$2:$E$11390) -> 218.0524 | F15: =SUMIF(Stundendaten!$M$2:$M$11390,A15,Stundendaten!$F$2:$F$11390) -> 38.5553 | G15: =COUNTIFS(Stundendaten!$M$2:$M$11390,A15,Stundendaten!$G$2:$G$11390,"ja") -> 528 | H15: =SUMIF(Stundendaten!$M$2:$M$11390,A15,Stundendaten!$J$2:$J$11390) -> 72.172586 | I15: =SUMIF(Stundendaten!$M$2:$M$11390,A15,Stundendaten!$K$2:$K$11390) -> 63.235196 | J15: =I15-H15 -> -8.9373899 | K15: =IF(E15>0,H15/E15*100,0) -> 33.098735 | L15: =AVERAGEIF(Stundendaten!$M$2:$M$11390,A15,Stundendaten!$I$2:$I$11390) -> 32.069235 | M15: =IF(E15>0,SUMIFS(Stundendaten!$E$2:$E$11390,Stundendaten!$M$2:$M$11390,A15,Stundendaten!$L$2:$L$11390,"ja")/E15,0) -> 0.11338009 | N15: =IF(AND(A15>=Einstellungen!$B$11,A15<=Einstellungen!$B$12),"ja","nein") -> ja | O15: =IF(B15>0,E15*C15/B15,0) -> 220.81256 | P15: =IF(B15>0,H15*C15/B15,0) -> 73.086163 | Q15: =IF(B15>0,I15*C15/B15,0) -> 64.035642
A16: 2025-12 | B16: =COUNTIF(Stundendaten!$M$2:$M$11390,A16) -> 670 | C16: 744 | D16: =C16-B16 -> 74 | E16: =SUMIF(Stundendaten!$M$2:$M$11390,A16,Stundendaten!$E$2:$E$11390) -> 277.4455 | F16: =SUMIF(Stundendaten!$M$2:$M$11390,A16,Stundendaten!$F$2:$F$11390) -> 23.9969 | G16: =COUNTIFS(Stundendaten!$M$2:$M$11390,A16,Stundendaten!$G$2:$G$11390,"ja") -> 535 | H16: =SUMIF(Stundendaten!$M$2:$M$11390,A16,Stundendaten!$J$2:$J$11390) -> 88.135945 | I16: =SUMIF(Stundendaten!$M$2:$M$11390,A16,Stundendaten!$K$2:$K$11390) -> 80.459195 | J16: =I16-H16 -> -7.6767499 | K16: =IF(E16>0,H16/E16*100,0) -> 31.76694 | L16: =AVERAGEIF(Stundendaten!$M$2:$M$11390,A16,Stundendaten!$I$2:$I$11390) -> 31.095407 | M16: =IF(E16>0,SUMIFS(Stundendaten!$E$2:$E$11390,Stundendaten!$M$2:$M$11390,A16,Stundendaten!$L$2:$L$11390,"ja")/E16,0) -> 0.15804401 | N16: =IF(AND(A16>=Einstellungen!$B$11,A16<=Einstellungen!$B$12),"ja","nein") -> ja | O16: =IF(B16>0,E16*C16/B16,0) -> 308.08873 | P16: =IF(B16>0,H16*C16/B16,0) -> 97.870363 | Q16: =IF(B16>0,I16*C16/B16,0) -> 89.345733
... A21: 2026-05 | B21: =COUNTIF(Stundendaten!$M$2:$M$11390,A21) -> 688 | C21: 744 | D21: =C21-B21 -> 56 | E21: =SUMIF(Stundendaten!$M$2:$M$11390,A21,Stundendaten!$E$2:$E$11390) -> 83.1349 | F21: =SUMIF(Stundendaten!$M$2:$M$11390,A21,Stundendaten!$F$2:$F$11390) -> 308.0448 | G21: =COUNTIFS(Stundendaten!$M$2:$M$11390,A21,Stundendaten!$G$2:$G$11390,"ja") -> 157 | H21: =SUMIF(Stundendaten!$M$2:$M$11390,A21,Stundendaten!$J$2:$J$11390) -> 29.505685 | I21: =SUMIF(Stundendaten!$M$2:$M$11390,A21,Stundendaten!$K$2:$K$11390) -> 24.109121 | J21: =I21-H21 -> -5.3965642 | K21: =IF(E21>0,H21/E21*100,0) -> 35.491334 | L21: =AVERAGEIF(Stundendaten!$M$2:$M$11390,A21,Stundendaten!$I$2:$I$11390) -> 30.361211 | M21: =IF(E21>0,SUMIFS(Stundendaten!$E$2:$E$11390,Stundendaten!$M$2:$M$11390,A21,Stundendaten!$L$2:$L$11390,"ja")/E21,0) -> 0.0068827893 | N21: =IF(AND(A21>=Einstellungen!$B$11,A21<=Einstellungen!$B$12),"ja","nein") -> ja | O21: =IF(B21>0,E21*C21/B21,0) -> 89.901694 | P21: =IF(B21>0,H21*C21/B21,0) -> 31.907311 | Q21: =IF(B21>0,I21*C21/B21,0) -> 26.071491
A22: Gesamt | B22: =SUM(B5:B21) -> 11389 | E22: =SUM(E5:E21) -> 2520.023 | F22: =SUM(F5:F21) -> 5163.8794 | G22: =SUM(G5:G21) -> 6939 | H22: =SUM(H5:H21) -> 821.92418 | I22: =SUM(I5:I21) -> 730.80667 | J22: =SUM(J5:J21) -> -91.117513 | K22: =H22/E22*100 -> 32.615741 | L22: =AVERAGE(Stundendaten!$I$2:$I$11390) -> 30.30025 | M22: =SUMIF(Stundendaten!$L$2:$L$11390,"ja",Stundendaten!$E$2:$E$11390)/E22 -> 0.16396073
A23: Jahresfenster (hochgerechnet) | N23: =COUNTIF(N5:N21,"ja")&" Monate" -> 12 Monate | O23: =SUMIF(N5:N21,"ja",O5:O21) -> 1949.0503 | P23: =SUMIF(N5:N21,"ja",P5:P21) -> 625.32763 | Q23: =SUMIF(N5:N21,"ja",Q5:Q21) -> 565.22459
A24: Jan. 2025 und Mai 2026 sind Teilmonate (Beginn/Ende der Zählerdaten). Die Sommerzeit-Umstellung erklärt 743/745 Stunden im März/Oktober.

Sheet Tagesprofil
A1: Wann ziehst du Strom – und was kostet er dann?
A2: Über den ganzen Zeitraum, nach Uhrzeit (deutsche Ortszeit). Die PV deckt die billigen Mittagsstunden; aus dem Netz kommt Strom vor allem abends und nachts.
A4: Stunde | B4: Netzbezug gesamt (kWh) | C4: Anteil am Netzbezug | D4: Einspeisung gesamt (kWh) | E4: Ø Endpreis dynamisch (ct/kWh) | F4: Festpreis (ct/kWh) | G4: Kosten dynamisch (€) | H4: Kosten Festpreis (€) | I4: Ersparnis dynamisch (€) | J4: Anteil Stunden mit Netzbezug
A5: 0 | B5: =SUMIF(Stundendaten!$O$2:$O$11390,A5,Stundendaten!$E$2:$E$11390) -> 115.3147 | C5: =B5/SUM($B$5:$B$28) -> 0.045759384 | D5: =SUMIF(Stundendaten!$O$2:$O$11390,A5,Stundendaten!$F$2:$F$11390) -> 3.8757 | E5: =AVERAGEIF(Stundendaten!$O$2:$O$11390,A5,Stundendaten!$I$2:$I$11390) -> 30.597189 | F5: =Einstellungen!$B$5 -> 29 | G5: =SUMIF(Stundendaten!$O$2:$O$11390,A5,Stundendaten!$J$2:$J$11390) -> 34.999146 | H5: =SUMIF(Stundendaten!$O$2:$O$11390,A5,Stundendaten!$K$2:$K$11390) -> 33.441263 | I5: =H5-G5 -> -1.5578827 | J5: =COUNTIFS(Stundendaten!$O$2:$O$11390,A5,Stundendaten!$G$2:$G$11390,"ja")/COUNTIF(Stundendaten!$O$2:$O$11390,A5) -> 0.81473684
A6: 1 | B6: =SUMIF(Stundendaten!$O$2:$O$11390,A6,Stundendaten!$E$2:$E$11390) -> 107.9912 | C6: =B6/SUM($B$5:$B$28) -> 0.04285326 | D6: =SUMIF(Stundendaten!$O$2:$O$11390,A6,Stundendaten!$F$2:$F$11390) -> 4.0024 | E6: =AVERAGEIF(Stundendaten!$O$2:$O$11390,A6,Stundendaten!$I$2:$I$11390) -> 30.004299 | F6: =Einstellungen!$B$5 -> 29 | G6: =SUMIF(Stundendaten!$O$2:$O$11390,A6,Stundendaten!$J$2:$J$11390) -> 32.123181 | H6: =SUMIF(Stundendaten!$O$2:$O$11390,A6,Stundendaten!$K$2:$K$11390) -> 31.317448 | I6: =H6-G6 -> -0.80573325 | J6: =COUNTIFS(Stundendaten!$O$2:$O$11390,A6,Stundendaten!$G$2:$G$11390,"ja")/COUNTIF(Stundendaten!$O$2:$O$11390,A6) -> 0.82489451
A7: 2 | B7: =SUMIF(Stundendaten!$O$2:$O$11390,A7,Stundendaten!$E$2:$E$11390) -> 100.1516 | C7: =B7/SUM($B$5:$B$28) -> 0.039742336 | D7: =SUMIF(Stundendaten!$O$2:$O$11390,A7,Stundendaten!$F$2:$F$11390) -> 3.9662 | E7: =AVERAGEIF(Stundendaten!$O$2:$O$11390,A7,Stundendaten!$I$2:$I$11390) -> 29.700035 | F7: =Einstellungen!$B$5 -> 29 | G7: =SUMIF(Stundendaten!$O$2:$O$11390,A7,Stundendaten!$J$2:$J$11390) -> 29.69145 | H7: =SUMIF(Stundendaten!$O$2:$O$11390,A7,Stundendaten!$K$2:$K$11390) -> 29.043964 | I7: =H7-G7 -> -0.64748606 | J7: =COUNTIFS(Stundendaten!$O$2:$O$11390,A7,Stundendaten!$G$2:$G$11390,"ja")/COUNTIF(Stundendaten!$O$2:$O$11390,A7) -> 0.84143763
A8: 3 | B8: =SUMIF(Stundendaten!$O$2:$O$11390,A8,Stundendaten!$E$2:$E$11390) -> 95.375 | C8: =B8/SUM($B$5:$B$28) -> 0.037846877 | D8: =SUMIF(Stundendaten!$O$2:$O$11390,A8,Stundendaten!$F$2:$F$11390) -> 3.9745 | E8: =AVERAGEIF(Stundendaten!$O$2:$O$11390,A8,Stundendaten!$I$2:$I$11390) -> 29.563437 | F8: =Einstellungen!$B$5 -> 29 | G8: =SUMIF(Stundendaten!$O$2:$O$11390,A8,Stundendaten!$J$2:$J$11390) -> 28.073311 | H8: =SUMIF(Stundendaten!$O$2:$O$11390,A8,Stundendaten!$K$2:$K$11390) -> 27.65875 | I8: =H8-G8 -> -0.41456076 | J8: =COUNTIFS(Stundendaten!$O$2:$O$11390,A8,Stundendaten!$G$2:$G$11390,"ja")/COUNTIF(Stundendaten!$O$2:$O$11390,A8) -> 0.85232068
A9: 4 | B9: =SUMIF(Stundendaten!$O$2:$O$11390,A9,Stundendaten!$E$2:$E$11390) -> 93.4299 | C9: =B9/SUM($B$5:$B$28) -> 0.037075019 | D9: =SUMIF(Stundendaten!$O$2:$O$11390,A9,Stundendaten!$F$2:$F$11390) -> 4.0754 | E9: =AVERAGEIF(Stundendaten!$O$2:$O$11390,A9,Stundendaten!$I$2:$I$11390) -> 29.726629 | F9: =Einstellungen!$B$5 -> 29 | G9: =SUMIF(Stundendaten!$O$2:$O$11390,A9,Stundendaten!$J$2:$J$11390) -> 27.606757 | H9: =SUMIF(Stundendaten!$O$2:$O$11390,A9,Stundendaten!$K$2:$K$11390) -> 27.094671 | I9: =H9-G9 -> -0.51208642 | J9: =COUNTIFS(Stundendaten!$O$2:$O$11390,A9,Stundendaten!$G$2:$G$11390,"ja")/COUNTIF(Stundendaten!$O$2:$O$11390,A9) -> 0.84599156
A10: 5 | B10: =SUMIF(Stundendaten!$O$2:$O$11390,A10,Stundendaten!$E$2:$E$11390) -> 94.3689 | C10: =B10/SUM($B$5:$B$28) -> 0.037447634 | D10: =SUMIF(Stundendaten!$O$2:$O$11390,A10,Stundendaten!$F$2:$F$11390) -> 3.8682 | E10: =AVERAGEIF(Stundendaten!$O$2:$O$11390,A10,Stundendaten!$I$2:$I$11390) -> 30.406946 | F10: =Einstellungen!$B$5 -> 29 | G10: =SUMIF(Stundendaten!$O$2:$O$11390,A10,Stundendaten!$J$2:$J$11390) -> 28.572916 | H10: =SUMIF(Stundendaten!$O$2:$O$11390,A10,Stundendaten!$K$2:$K$11390) -> 27.366981 | I10: =H10-G10 -> -1.2059346 | J10: =COUNTIFS(Stundendaten!$O$2:$O$11390,A10,Stundendaten!$G$2:$G$11390,"ja")/COUNTIF(Stundendaten!$O$2:$O$11390,A10) -> 0.86708861
A11: 6 | B11: =SUMIF(Stundendaten!$O$2:$O$11390,A11,Stundendaten!$E$2:$E$11390) -> 103.6598 | C11: =B11/SUM($B$5:$B$28) -> 0.041134466 | D11: =SUMIF(Stundendaten!$O$2:$O$11390,A11,Stundendaten!$F$2:$F$11390) -> 3.2122 | E11: =AVERAGEIF(Stundendaten!$O$2:$O$11390,A11,Stundendaten!$I$2:$I$11390) -> 32.023968 | F11: =Einstellungen!$B$5 -> 29 | G11: =SUMIF(Stundendaten!$O$2:$O$11390,A11,Stundendaten!$J$2:$J$11390) -> 33.003125 | H11: =SUMIF(Stundendaten!$O$2:$O$11390,A11,Stundendaten!$K$2:$K$11390) -> 30.061342 | I11: =H11-G11 -> -2.9417829 | J11: =COUNTIFS(Stundendaten!$O$2:$O$11390,A11,Stundendaten!$G$2:$G$11390,"ja")/COUNTIF(Stundendaten!$O$2:$O$11390,A11) -> 0.8649789
A12: 7 | B12: =SUMIF(Stundendaten!$O$2:$O$11390,A12,Stundendaten!$E$2:$E$11390) -> 105.3093 | C12: =B12/SUM($B$5:$B$28) -> 0.041789023 | D12: =SUMIF(Stundendaten!$O$2:$O$11390,A12,Stundendaten!$F$2:$F$11390) -> 30.3444 | E12: =AVERAGEIF(Stundendaten!$O$2:$O$11390,A12,Stundendaten!$I$2:$I$11390) -> 33.257917 | F12: =Einstellungen!$B$5 -> 29 | G12: =SUMIF(Stundendaten!$O$2:$O$11390,A12,Stundendaten!$J$2:$J$11390) -> 34.835798 | H12: =SUMIF(Stundendaten!$O$2:$O$11390,A12,Stundendaten!$K$2:$K$11390) -> 30.539697 | I12: =H12-G12 -> -4.2961014 | J12: =COUNTIFS(Stundendaten!$O$2:$O$11390,A12,Stundendaten!$G$2:$G$11390,"ja")/COUNTIF(Stundendaten!$O$2:$O$11390,A12) -> 0.6835443
A13: 8 | B13: =SUMIF(Stundendaten!$O$2:$O$11390,A13,Stundendaten!$E$2:$E$11390) -> 78.5943 | C13: =B13/SUM($B$5:$B$28) -> 0.03118793 | D13: =SUMIF(Stundendaten!$O$2:$O$11390,A13,Stundendaten!$F$2:$F$11390) -> 175.1504 | E13: =AVERAGEIF(Stundendaten!$O$2:$O$11390,A13,Stundendaten!$I$2:$I$11390) -> 32.586714 | F13: =Einstellungen!$B$5 -> 29 | G13: =SUMIF(Stundendaten!$O$2:$O$11390,A13,Stundendaten!$J$2:$J$11390) -> 26.856504 | H13: =SUMIF(Stundendaten!$O$2:$O$11390,A13,Stundendaten!$K$2:$K$11390) -> 22.792347 | I13: =H13-G13 -> -4.0641575 | J13: =COUNTIFS(Stundendaten!$O$2:$O$11390,A13,Stundendaten!$G$2:$G$11390,"ja")/COUNTIF(Stundendaten!$O$2:$O$11390,A13) -> 0.50212766
A14: 9 | B14: =SUMIF(Stundendaten!$O$2:$O$11390,A14,Stundendaten!$E$2:$E$11390) -> 64.8701 | C14: =B14/SUM($B$5:$B$28) -> 0.025741868 | D14: =SUMIF(Stundendaten!$O$2:$O$11390,A14,Stundendaten!$F$2:$F$11390) -> 361.0754 | E14: =AVERAGEIF(Stundendaten!$O$2:$O$11390,A14,Stundendaten!$I$2:$I$11390) -> 30.214497 | F14: =Einstellungen!$B$5 -> 29 | G14: =SUMIF(Stundendaten!$O$2:$O$11390,A14,Stundendaten!$J$2:$J$11390) -> 21.388714 | H14: =SUMIF(Stundendaten!$O$2:$O$11390,A14,Stundendaten!$K$2:$K$11390) -> 18.812329 | I14: =H14-G14 -> -2.5763847 | J14: =COUNTIFS(Stundendaten!$O$2:$O$11390,A14,Stundendaten!$G$2:$G$11390,"ja")/COUNTIF(Stundendaten!$O$2:$O$11390,A14) -> 0.37234043
A15: 10 | B15: =SUMIF(Stundendaten!$O$2:$O$11390,A15,Stundendaten!$E$2:$E$11390) -> 47.3756 | C15: =B15/SUM($B$5:$B$28) -> 0.01879967 | D15: =SUMIF(Stundendaten!$O$2:$O$11390,A15,Stundendaten!$F$2:$F$11390) -> 552.6421 | E15: =AVERAGEIF(Stundendaten!$O$2:$O$11390,A15,Stundendaten!$I$2:$I$11390) -> 27.893675 | F15: =Einstellungen!$B$5 -> 29 | G15: =SUMIF(Stundendaten!$O$2:$O$11390,A15,Stundendaten!$J$2:$J$11390) -> 14.91032 | H15: =SUMIF(Stundendaten!$O$2:$O$11390,A15,Stundendaten!$K$2:$K$11390) -> 13.738924 | I15: =H15-G15 -> -1.1713964 | J15: =COUNTIFS(Stundendaten!$O$2:$O$11390,A15,Stundendaten!$G$2:$G$11390,"ja")/COUNTIF(Stundendaten!$O$2:$O$11390,A15) -> 0.28177966
A16: 11 | B16: =SUMIF(Stundendaten!$O$2:$O$11390,A16,Stundendaten!$E$2:$E$11390) -> 54.9932 | C16: =B16/SUM($B$5:$B$28) -> 0.021822499 | D16: =SUMIF(Stundendaten!$O$2:$O$11390,A16,Stundendaten!$F$2:$F$11390) -> 682.5247 | E16: =AVERAGEIF(Stundendaten!$O$2:$O$11390,A16,Stundendaten!$I$2:$I$11390) -> 26.297695 | F16: =Einstellungen!$B$5 -> 29 | G16: =SUMIF(Stundendaten!$O$2:$O$11390,A16,Stundendaten!$J$2:$J$11390) -> 16.055602 | H16: =SUMIF(Stundendaten!$O$2:$O$11390,A16,Stundendaten!$K$2:$K$11390) -> 15.948028 | I16: =H16-G16 -> -0.10757417 | J16: =COUNTIFS(Stundendaten!$O$2:$O$11390,A16,Stundendaten!$G$2:$G$11390,"ja")/COUNTIF(Stundendaten!$O$2:$O$11390,A16) -> 0.25792812
... A28: 23 | B28: =SUMIF(Stundendaten!$O$2:$O$11390,A28,Stundendaten!$E$2:$E$11390) -> 124.5439 | C28: =B28/SUM($B$5:$B$28) -> 0.049421731 | D28: =SUMIF(Stundendaten!$O$2:$O$11390,A28,Stundendaten!$F$2:$F$11390) -> 4.2232 | E28: =AVERAGEIF(Stundendaten!$O$2:$O$11390,A28,Stundendaten!$I$2:$I$11390) -> 31.043335 | F28: =Einstellungen!$B$5 -> 29 | G28: =SUMIF(Stundendaten!$O$2:$O$11390,A28,Stundendaten!$J$2:$J$11390) -> 38.498835 | H28: =SUMIF(Stundendaten!$O$2:$O$11390,A28,Stundendaten!$K$2:$K$11390) -> 36.117731 | I28: =H28-G28 -> -2.381104 | J28: =COUNTIFS(Stundendaten!$O$2:$O$11390,A28,Stundendaten!$G$2:$G$11390,"ja")/COUNTIF(Stundendaten!$O$2:$O$11390,A28) -> 0.8197065
A29: Summe | B29: =SUM(B5:B28) -> 2520.023 | C29: =SUM(C5:C28) -> 1 | D29: =SUM(D5:D28) -> 5163.8794 | G29: =SUM(G5:G28) -> 821.92418 | H29: =SUM(H5:H28) -> 730.80667 | I29: =SUM(I5:I28) -> -91.117513

Sheet Datenlücken
A1: Zeiträume ohne Zählerdaten
A2: In diesen Stunden hat Home Assistant nichts aufgezeichnet. Sie fehlen in allen Summen – im Fazit wird für die Jahresrechnung hochgerechnet.
A4: Von (Ortszeit) | B4: Bis (Ortszeit) | C4: Fehlende Stunden
A5: 27.01.2025 23:00 | B5: 28.01.2025 16:00 | C5: 18
A6: 28.01.2025 21:00 | B6: 28.01.2025 21:00 | C6: 1
A7: 29.01.2025 01:00 | B7: 29.01.2025 14:00 | C7: 14
A8: 23.04.2025 15:00 | B8: 24.04.2025 07:00 | C8: 17
A9: 04.06.2025 00:00 | B9: 04.06.2025 11:00 | C9: 12
A10: 23.08.2025 08:00 | B10: 23.08.2025 10:00 | C10: 3
A11: 01.09.2025 08:00 | B11: 01.09.2025 13:00 | C11: 6
A12: 03.09.2025 08:00 | B12: 05.09.2025 06:00 | C12: 47
A13: 07.09.2025 08:00 | B13: 09.09.2025 13:00 | C13: 54
A14: 06.11.2025 00:00 | B14: 06.11.2025 08:00 | C14: 9
A15: 27.12.2025 08:00 | B15: 30.12.2025 09:00 | C15: 74
A16: 10.02.2026 18:00 | B16: 10.02.2026 18:00 | C16: 1
... A19: 18.04.2026 09:00 | B19: 18.04.2026 09:00 | C19: 1
A20: Summe | C20: =SUM(C5:C19) -> 294
